
{
	"name" : "",
	"sprite" : 
	[
		
		{
			"add color" : "",
			"angle" : 0.0,
			"filepath" : "6205-biankuang-1.png",
			"multi color" : "",
			"name" : "",
			"position" : 
			{
				"x" : 0.0,
				"y" : 0.0
			},
			"x mirror" : false,
			"x scale" : 47.0,
			"x shear" : 0.0,
			"y mirror" : false,
			"y scale" : 52.50,
			"y shear" : 0.0
		},
		
		{
			"add color" : "",
			"angle" : 0.0,
			"filepath" : "6106-tongyong-1.png",
			"multi color" : "",
			"name" : "",
			"position" : 
			{
				"x" : -66.30001831054688,
				"y" : 10.0
			},
			"x mirror" : false,
			"x scale" : 0.4499999880790710,
			"x shear" : 0.0,
			"y mirror" : false,
			"y scale" : 0.4499999880790710,
			"y shear" : 0.0
		},
		
		{
			"add color" : "",
			"angle" : 0.0,
			"filepath" : "6105-tongyong-1.png",
			"multi color" : "",
			"name" : "",
			"position" : 
			{
				"x" : -63.65001678466797,
				"y" : -57.250
			},
			"x mirror" : false,
			"x scale" : 0.4499999880790710,
			"x shear" : 0.0,
			"y mirror" : false,
			"y scale" : 0.4499999880790710,
			"y shear" : 0.0
		},
		
		{
			"add color" : "",
			"angle" : 0.0,
			"filepath" : "tttt2_fontblank.json",
			"multi color" : "",
			"name" : "title",
			"position" : 
			{
				"x" : -3.000015258789063,
				"y" : 72.0
			},
			"x mirror" : false,
			"x scale" : 1.0,
			"x shear" : 0.0,
			"y mirror" : false,
			"y scale" : 1.0,
			"y shear" : 0.0
		},
		
		{
			"add color" : "",
			"angle" : 0.0,
			"filepath" : "ttttt3_fontblank.json",
			"multi color" : "",
			"name" : "gold_amount",
			"position" : 
			{
				"x" : 17.99998474121094,
				"y" : 11.250
			},
			"x mirror" : false,
			"x scale" : 1.0,
			"x shear" : 0.0,
			"y mirror" : false,
			"y scale" : 1.0,
			"y shear" : 0.0
		},
		
		{
			"add color" : "",
			"angle" : 0.0,
			"filepath" : "ttttt3_fontblank.json",
			"multi color" : "",
			"name" : "elixir_amount",
			"position" : 
			{
				"x" : 17.99998474121094,
				"y" : -60.0
			},
			"x mirror" : false,
			"x scale" : 1.0,
			"x shear" : 0.0,
			"y mirror" : false,
			"y scale" : 1.0,
			"y shear" : 0.0
		},
		
		{
			"add color" : "",
			"angle" : 0.0,
			"filepath" : "info_icon_bg_scale9.json",
			"multi color" : "",
			"name" : "",
			"position" : 
			{
				"x" : 0.0,
				"y" : 0.0
			},
			"x mirror" : false,
			"x scale" : 1.058201074600220,
			"x shear" : 0.0,
			"y mirror" : false,
			"y scale" : 0.8593750,
			"y shear" : 0.0
		}
	]
}
