
{
	"fps" : 30,
	"layer" : 
	[
		
		{
			"frame" : 
			[
				
				{
					"actor" : 
					[
						
						{
							"add color" : "",
							"angle" : 0.0,
							"filepath" : "..\\..\\pngs\\1031_1_2.png",
							"multi color" : "",
							"name" : "",
							"position" : 
							{
								"x" : -0.8939876556396484,
								"y" : -9.971755981445313
							},
							"x mirror" : false,
							"x scale" : 1.0,
							"x shear" : 0.0,
							"y mirror" : false,
							"y scale" : 1.0,
							"y shear" : 0.0
						},
						
						{
							"add color" : "",
							"angle" : 0.0,
							"filepath" : "..\\..\\pngs\\1031_1_1.png",
							"multi color" : "",
							"name" : "",
							"position" : 
							{
								"x" : -0.04579019546508789,
								"y" : -10.12356185913086
							},
							"x mirror" : false,
							"x scale" : 1.0,
							"x shear" : 0.0,
							"y mirror" : false,
							"y scale" : 1.0,
							"y shear" : 0.0
						}
					],
					"id" : 0,
					"time" : 1,
					"tween" : true
				},
				
				{
					"actor" : 
					[
						
						{
							"add color" : "",
							"angle" : 0.0,
							"filepath" : "..\\..\\pngs\\1031_1_2.png",
							"multi color" : "",
							"name" : "",
							"position" : 
							{
								"x" : -0.8939876556396484,
								"y" : -9.971755981445313
							},
							"x mirror" : false,
							"x scale" : 1.0,
							"x shear" : 0.0,
							"y mirror" : false,
							"y scale" : 1.0,
							"y shear" : 0.0
						},
						
						{
							"add color" : "",
							"angle" : 0.03299106657505035,
							"filepath" : "..\\..\\pngs\\1031_1_1.png",
							"multi color" : "",
							"name" : "",
							"position" : 
							{
								"x" : -0.04579019546508789,
								"y" : -10.12356185913086
							},
							"x mirror" : false,
							"x scale" : 1.0,
							"x shear" : 0.0,
							"y mirror" : false,
							"y scale" : 1.0,
							"y shear" : 0.0
						}
					],
					"id" : 0,
					"time" : 4,
					"tween" : true
				},
				
				{
					"actor" : 
					[
						
						{
							"add color" : "",
							"angle" : -0.07493629306554794,
							"filepath" : "..\\..\\pngs\\1031_1_2.png",
							"multi color" : "",
							"name" : "",
							"position" : 
							{
								"x" : -1.200000047683716,
								"y" : -9.971755981445313
							},
							"x mirror" : false,
							"x scale" : 1.0,
							"x shear" : 0.0,
							"y mirror" : false,
							"y scale" : 1.0,
							"y shear" : 0.0
						},
						
						{
							"add color" : "",
							"angle" : 0.05581784993410111,
							"filepath" : "..\\..\\pngs\\1031_1_1.png",
							"multi color" : "",
							"name" : "",
							"position" : 
							{
								"x" : -0.04579019546508789,
								"y" : -10.12356185913086
							},
							"x mirror" : false,
							"x scale" : 1.0,
							"x shear" : 0.0,
							"y mirror" : false,
							"y scale" : 1.0,
							"y shear" : 0.0
						}
					],
					"id" : 0,
					"time" : 7,
					"tween" : true
				},
				
				{
					"actor" : 
					[
						
						{
							"add color" : "",
							"angle" : -0.03037267737090588,
							"filepath" : "..\\..\\pngs\\1031_1_2.png",
							"multi color" : "",
							"name" : "",
							"position" : 
							{
								"x" : -1.200000047683716,
								"y" : -9.971755981445313
							},
							"x mirror" : false,
							"x scale" : 1.0,
							"x shear" : 0.0,
							"y mirror" : false,
							"y scale" : 1.0,
							"y shear" : 0.0
						},
						
						{
							"add color" : "",
							"angle" : -0.02083072811365128,
							"filepath" : "..\\..\\pngs\\1031_1_1.png",
							"multi color" : "",
							"name" : "",
							"position" : 
							{
								"x" : -1.045790195465088,
								"y" : -10.12356185913086
							},
							"x mirror" : false,
							"x scale" : 1.0,
							"x shear" : 0.0,
							"y mirror" : false,
							"y scale" : 1.0,
							"y shear" : 0.0
						}
					],
					"id" : 0,
					"time" : 10,
					"tween" : true
				},
				
				{
					"actor" : 
					[
						
						{
							"add color" : "",
							"angle" : -0.03000000119209290,
							"filepath" : "..\\..\\pngs\\1031_1_2.png",
							"multi color" : "",
							"name" : "",
							"position" : 
							{
								"x" : -1.200000047683716,
								"y" : -9.971755981445313
							},
							"x mirror" : false,
							"x scale" : 1.0,
							"x shear" : 0.0,
							"y mirror" : false,
							"y scale" : 1.0,
							"y shear" : 0.0
						},
						
						{
							"add color" : "",
							"angle" : -0.02083072811365128,
							"filepath" : "..\\..\\pngs\\1031_1_1.png",
							"multi color" : "",
							"name" : "",
							"position" : 
							{
								"x" : -1.045790195465088,
								"y" : -10.12356185913086
							},
							"x mirror" : false,
							"x scale" : 1.0,
							"x shear" : 0.0,
							"y mirror" : false,
							"y scale" : 1.0,
							"y shear" : 0.0
						}
					],
					"id" : 0,
					"time" : 12,
					"tween" : false
				}
			],
			"name" : "Layer0"
		}
	],
	"name" : ""
}
