
{
	"fps" : 30,
	"layer" : 
	[
		
		{
			"frame" : 
			[
				
				{
					"actor" : 
					[
						
						{
							"add color" : "0x00000000",
							"angle" : 0.0,
							"clip" : false,
							"filepath" : "1888_complex.json",
							"multi color" : "0xffffff0c",
							"name" : "",
							"position" : 
							{
								"x" : 0.0,
								"y" : 0.0
							},
							"tag" : "",
							"x mirror" : false,
							"x offset" : 0.0,
							"x scale" : 2.4316406250,
							"x shear" : 0.0,
							"y mirror" : false,
							"y offset" : 0.0,
							"y scale" : 2.4316406250,
							"y shear" : 0.0
						},
						
						{
							"add color" : "0x00110007",
							"angle" : 0.5208448767662048,
							"clip" : false,
							"filepath" : "1901_complex.json",
							"multi color" : "0x5b3cffff",
							"name" : "",
							"position" : 
							{
								"x" : 0.0,
								"y" : 217.50
							},
							"tag" : "",
							"x mirror" : false,
							"x offset" : 0.0,
							"x scale" : 1.497382402420044,
							"x shear" : 0.0,
							"y mirror" : false,
							"y offset" : 0.0,
							"y scale" : 1.497382402420044,
							"y shear" : 0.0
						}
					],
					"time" : 1
				},
				
				{
					"actor" : 
					[
						
						{
							"add color" : "0x00000000",
							"angle" : 0.0,
							"clip" : false,
							"filepath" : "1888_complex.json",
							"multi color" : "0xffffff0e",
							"name" : "",
							"position" : 
							{
								"x" : 0.0,
								"y" : 0.0
							},
							"tag" : "",
							"x mirror" : false,
							"x offset" : 0.0,
							"x scale" : 2.33105468750,
							"x shear" : 0.0,
							"y mirror" : false,
							"y offset" : 0.0,
							"y scale" : 2.33105468750,
							"y shear" : 0.0
						},
						
						{
							"add color" : "0x00110007",
							"angle" : 0.5200369954109192,
							"clip" : false,
							"filepath" : "1901_complex.json",
							"multi color" : "0x5b3cffff",
							"name" : "",
							"position" : 
							{
								"x" : 0.0,
								"y" : 216.81250
							},
							"tag" : "",
							"x mirror" : false,
							"x offset" : 0.0,
							"x scale" : 1.495563983917236,
							"x shear" : 0.0,
							"y mirror" : false,
							"y offset" : 0.0,
							"y scale" : 1.495563983917236,
							"y shear" : 0.0
						}
					],
					"time" : 2
				},
				
				{
					"actor" : 
					[
						
						{
							"add color" : "0x00000000",
							"angle" : 0.0,
							"clip" : false,
							"filepath" : "1888_complex.json",
							"multi color" : "0xffffff11",
							"name" : "",
							"position" : 
							{
								"x" : 0.0,
								"y" : 0.0
							},
							"tag" : "",
							"x mirror" : false,
							"x offset" : 0.0,
							"x scale" : 2.230468750,
							"x shear" : 0.0,
							"y mirror" : false,
							"y offset" : 0.0,
							"y scale" : 2.230468750,
							"y shear" : 0.0
						},
						
						{
							"add color" : "0x00110007",
							"angle" : 0.5079261660575867,
							"clip" : false,
							"filepath" : "1901_complex.json",
							"multi color" : "0x5b3cffff",
							"name" : "",
							"position" : 
							{
								"x" : 0.0,
								"y" : 214.56250
							},
							"tag" : "",
							"x mirror" : false,
							"x offset" : 0.0,
							"x scale" : 1.489843010902405,
							"x shear" : 0.0,
							"y mirror" : false,
							"y offset" : 0.0,
							"y scale" : 1.489843010902405,
							"y shear" : 0.0
						}
					],
					"time" : 3
				},
				
				{
					"actor" : 
					[
						
						{
							"add color" : "0x00000000",
							"angle" : 0.0,
							"clip" : false,
							"filepath" : "1888_complex.json",
							"multi color" : "0xffffff16",
							"name" : "",
							"position" : 
							{
								"x" : 0.0,
								"y" : 0.0
							},
							"tag" : "",
							"x mirror" : false,
							"x offset" : 0.0,
							"x scale" : 2.128906250,
							"x shear" : 0.0,
							"y mirror" : false,
							"y offset" : 0.0,
							"y scale" : 2.128906250,
							"y shear" : 0.0
						},
						
						{
							"add color" : "0x00110007",
							"angle" : 0.4937181770801544,
							"clip" : false,
							"filepath" : "1901_complex.json",
							"multi color" : "0x5b3cffff",
							"name" : "",
							"position" : 
							{
								"x" : 0.0,
								"y" : 211.06250
							},
							"tag" : "",
							"x mirror" : false,
							"x offset" : 0.0,
							"x scale" : 1.481628060340881,
							"x shear" : 0.0,
							"y mirror" : false,
							"y offset" : 0.0,
							"y scale" : 1.481628060340881,
							"y shear" : 0.0
						}
					],
					"time" : 4
				},
				
				{
					"actor" : 
					[
						
						{
							"add color" : "0x00000000",
							"angle" : 0.0,
							"clip" : false,
							"filepath" : "1888_complex.json",
							"multi color" : "0xffffff19",
							"name" : "",
							"position" : 
							{
								"x" : 0.0,
								"y" : 0.0
							},
							"tag" : "",
							"x mirror" : false,
							"x offset" : 0.0,
							"x scale" : 2.02832031250,
							"x shear" : 0.0,
							"y mirror" : false,
							"y offset" : 0.0,
							"y scale" : 2.02832031250,
							"y shear" : 0.0
						},
						
						{
							"add color" : "0x00110007",
							"angle" : 0.4684052169322968,
							"clip" : false,
							"filepath" : "1901_complex.json",
							"multi color" : "0x5b3cffff",
							"name" : "",
							"position" : 
							{
								"x" : -0.06250,
								"y" : 205.93750
							},
							"tag" : "",
							"x mirror" : false,
							"x offset" : 0.0,
							"x scale" : 1.468746423721314,
							"x shear" : 0.0,
							"y mirror" : false,
							"y offset" : 0.0,
							"y scale" : 1.468746423721314,
							"y shear" : 0.0
						}
					],
					"time" : 5
				},
				
				{
					"actor" : 
					[
						
						{
							"add color" : "0x00000000",
							"angle" : 0.0,
							"clip" : false,
							"filepath" : "1888_complex.json",
							"multi color" : "0xffffff1e",
							"name" : "",
							"position" : 
							{
								"x" : 0.0,
								"y" : 0.0
							},
							"tag" : "",
							"x mirror" : false,
							"x offset" : 0.0,
							"x scale" : 1.9277343750,
							"x shear" : 0.0,
							"y mirror" : false,
							"y offset" : 0.0,
							"y scale" : 1.9277343750,
							"y shear" : 0.0
						},
						
						{
							"add color" : "0x00110007",
							"angle" : 0.4378042519092560,
							"clip" : false,
							"filepath" : "1901_complex.json",
							"multi color" : "0x5b3cffff",
							"name" : "",
							"position" : 
							{
								"x" : 0.0,
								"y" : 199.50
							},
							"tag" : "",
							"x mirror" : false,
							"x offset" : 0.0,
							"x scale" : 1.453492760658264,
							"x shear" : 0.0,
							"y mirror" : false,
							"y offset" : 0.0,
							"y scale" : 1.453492760658264,
							"y shear" : 0.0
						}
					],
					"time" : 6
				},
				
				{
					"actor" : 
					[
						
						{
							"add color" : "0x00000000",
							"angle" : 0.0,
							"clip" : false,
							"filepath" : "1888_complex.json",
							"multi color" : "0xffffff20",
							"name" : "",
							"position" : 
							{
								"x" : 0.0,
								"y" : 0.0
							},
							"tag" : "",
							"x mirror" : false,
							"x offset" : 0.0,
							"x scale" : 1.8261718750,
							"x shear" : 0.0,
							"y mirror" : false,
							"y offset" : 0.0,
							"y scale" : 1.8261718750,
							"y shear" : 0.0
						},
						
						{
							"add color" : "0x00110007",
							"angle" : 0.4023877680301666,
							"clip" : false,
							"filepath" : "1901_complex.json",
							"multi color" : "0x5b3cffff",
							"name" : "",
							"position" : 
							{
								"x" : 0.0,
								"y" : 191.56250
							},
							"tag" : "",
							"x mirror" : false,
							"x offset" : 0.0,
							"x scale" : 1.433860421180725,
							"x shear" : 0.0,
							"y mirror" : false,
							"y offset" : 0.0,
							"y scale" : 1.433860421180725,
							"y shear" : 0.0
						}
					],
					"time" : 7
				},
				
				{
					"actor" : 
					[
						
						{
							"add color" : "0x00000000",
							"angle" : 0.0,
							"clip" : false,
							"filepath" : "1888_complex.json",
							"multi color" : "0xffffff25",
							"name" : "",
							"position" : 
							{
								"x" : 0.0,
								"y" : 0.0
							},
							"tag" : "",
							"x mirror" : false,
							"x offset" : 0.0,
							"x scale" : 1.72558593750,
							"x shear" : 0.0,
							"y mirror" : false,
							"y offset" : 0.0,
							"y scale" : 1.72558593750,
							"y shear" : 0.0
						},
						
						{
							"add color" : "0x00110007",
							"angle" : 0.3585276603698731,
							"clip" : false,
							"filepath" : "1901_complex.json",
							"multi color" : "0x5b3cffff",
							"name" : "",
							"position" : 
							{
								"x" : 0.0,
								"y" : 182.06250
							},
							"tag" : "",
							"x mirror" : false,
							"x offset" : 0.0,
							"x scale" : 1.411008834838867,
							"x shear" : 0.0,
							"y mirror" : false,
							"y offset" : 0.0,
							"y scale" : 1.411008834838867,
							"y shear" : 0.0
						}
					],
					"time" : 8
				},
				
				{
					"actor" : 
					[
						
						{
							"add color" : "0x00000000",
							"angle" : 0.0,
							"clip" : false,
							"filepath" : "1888_complex.json",
							"multi color" : "0xffffff28",
							"name" : "",
							"position" : 
							{
								"x" : 0.0,
								"y" : 0.0
							},
							"tag" : "",
							"x mirror" : false,
							"x offset" : 0.0,
							"x scale" : 1.6250,
							"x shear" : 0.0,
							"y mirror" : false,
							"y offset" : 0.0,
							"y scale" : 1.6250,
							"y shear" : 0.0
						},
						
						{
							"add color" : "0x00110007",
							"angle" : 0.310159444808960,
							"clip" : false,
							"filepath" : "1901_complex.json",
							"multi color" : "0x5b3cffff",
							"name" : "",
							"position" : 
							{
								"x" : -0.06250,
								"y" : 171.250
							},
							"tag" : "",
							"x mirror" : false,
							"x offset" : 0.0,
							"x scale" : 1.385442495346069,
							"x shear" : 0.0,
							"y mirror" : false,
							"y offset" : 0.0,
							"y scale" : 1.385442495346069,
							"y shear" : 0.0
						}
					],
					"time" : 9
				},
				
				{
					"actor" : 
					[
						
						{
							"add color" : "0x00000000",
							"angle" : 0.0,
							"clip" : false,
							"filepath" : "1888_complex.json",
							"multi color" : "0xffffff2d",
							"name" : "",
							"position" : 
							{
								"x" : 0.0,
								"y" : 0.0
							},
							"tag" : "",
							"x mirror" : false,
							"x offset" : 0.0,
							"x scale" : 1.52441406250,
							"x shear" : 0.0,
							"y mirror" : false,
							"y offset" : 0.0,
							"y scale" : 1.52441406250,
							"y shear" : 0.0
						},
						
						{
							"add color" : "0x00110007",
							"angle" : 0.2533642053604126,
							"clip" : false,
							"filepath" : "1901_complex.json",
							"multi color" : "0x5b3cffff",
							"name" : "",
							"position" : 
							{
								"x" : -0.06250,
								"y" : 159.06250
							},
							"tag" : "",
							"x mirror" : false,
							"x offset" : 0.0,
							"x scale" : 1.355783939361572,
							"x shear" : 0.0,
							"y mirror" : false,
							"y offset" : 0.0,
							"y scale" : 1.355783939361572,
							"y shear" : 0.0
						}
					],
					"time" : 10
				},
				
				{
					"actor" : 
					[
						
						{
							"add color" : "0x00000000",
							"angle" : 0.0,
							"clip" : false,
							"filepath" : "1888_complex.json",
							"multi color" : "0xffffff30",
							"name" : "",
							"position" : 
							{
								"x" : 0.0,
								"y" : 0.0
							},
							"tag" : "",
							"x mirror" : false,
							"x offset" : 0.0,
							"x scale" : 1.42285156250,
							"x shear" : 0.0,
							"y mirror" : false,
							"y offset" : 0.0,
							"y scale" : 1.42285156250,
							"y shear" : 0.0
						},
						
						{
							"add color" : "0x00110007",
							"angle" : 0.1887051612138748,
							"clip" : false,
							"filepath" : "1901_complex.json",
							"multi color" : "0x5b3cffff",
							"name" : "",
							"position" : 
							{
								"x" : 0.0,
								"y" : 145.31250
							},
							"tag" : "",
							"x mirror" : false,
							"x offset" : 0.0,
							"x scale" : 1.322301745414734,
							"x shear" : 0.0,
							"y mirror" : false,
							"y offset" : 0.0,
							"y scale" : 1.322301745414734,
							"y shear" : 0.0
						}
					],
					"time" : 11
				},
				
				{
					"actor" : 
					[
						
						{
							"add color" : "0x00000000",
							"angle" : 0.0,
							"clip" : false,
							"filepath" : "1888_complex.json",
							"multi color" : "0xffffff35",
							"name" : "",
							"position" : 
							{
								"x" : 0.0,
								"y" : 0.0
							},
							"tag" : "",
							"x mirror" : false,
							"x offset" : 0.0,
							"x scale" : 1.3222656250,
							"x shear" : 0.0,
							"y mirror" : false,
							"y offset" : 0.0,
							"y scale" : 1.3222656250,
							"y shear" : 0.0
						},
						
						{
							"add color" : "0x00110007",
							"angle" : 0.1187953129410744,
							"clip" : false,
							"filepath" : "1901_complex.json",
							"multi color" : "0x5b3cffff",
							"name" : "",
							"position" : 
							{
								"x" : 0.0,
								"y" : 130.1250
							},
							"tag" : "",
							"x mirror" : false,
							"x offset" : 0.0,
							"x scale" : 1.285426616668701,
							"x shear" : 0.0,
							"y mirror" : false,
							"y offset" : 0.0,
							"y scale" : 1.285426616668701,
							"y shear" : 0.0
						}
					],
					"time" : 12
				},
				
				{
					"actor" : 
					[
						
						{
							"add color" : "0x00000000",
							"angle" : 0.0,
							"clip" : false,
							"filepath" : "1888_complex.json",
							"multi color" : "0xffffff37",
							"name" : "",
							"position" : 
							{
								"x" : 0.0,
								"y" : 0.0
							},
							"tag" : "",
							"x mirror" : false,
							"x offset" : 0.0,
							"x scale" : 1.22167968750,
							"x shear" : 0.0,
							"y mirror" : false,
							"y offset" : 0.0,
							"y scale" : 1.22167968750,
							"y shear" : 0.0
						},
						
						{
							"add color" : "0x00110007",
							"angle" : 0.04392776638269424,
							"clip" : false,
							"filepath" : "1901_complex.json",
							"multi color" : "0x5b3cffff",
							"name" : "",
							"position" : 
							{
								"x" : 0.0,
								"y" : 113.56250
							},
							"tag" : "",
							"x mirror" : false,
							"x offset" : 0.0,
							"x scale" : 1.245342016220093,
							"x shear" : 0.0,
							"y mirror" : false,
							"y offset" : 0.0,
							"y scale" : 1.245342016220093,
							"y shear" : 0.0
						}
					],
					"time" : 13
				},
				
				{
					"actor" : 
					[
						
						{
							"add color" : "0x00000000",
							"angle" : 0.0,
							"clip" : false,
							"filepath" : "1888_complex.json",
							"multi color" : "0xffffff3c",
							"name" : "",
							"position" : 
							{
								"x" : 0.0,
								"y" : 0.0
							},
							"tag" : "",
							"x mirror" : false,
							"x offset" : 0.0,
							"x scale" : 1.121093750,
							"x shear" : 0.0,
							"y mirror" : false,
							"y offset" : 0.0,
							"y scale" : 1.121093750,
							"y shear" : 0.0
						},
						
						{
							"add color" : "0x00110007",
							"angle" : -0.03497352823615074,
							"clip" : false,
							"filepath" : "1901_complex.json",
							"multi color" : "0x5b3cffff",
							"name" : "",
							"position" : 
							{
								"x" : 0.0,
								"y" : 95.3750
							},
							"tag" : "",
							"x mirror" : false,
							"x offset" : 0.0,
							"x scale" : 1.200929760932922,
							"x shear" : 0.0,
							"y mirror" : false,
							"y offset" : 0.0,
							"y scale" : 1.200929760932922,
							"y shear" : 0.0
						}
					],
					"time" : 14
				},
				
				{
					"actor" : 
					[
						
						{
							"add color" : "0x00000000",
							"angle" : 0.0,
							"clip" : false,
							"filepath" : "1888_complex.json",
							"multi color" : "0xffffff3f",
							"name" : "",
							"position" : 
							{
								"x" : 0.0,
								"y" : 0.0
							},
							"tag" : "",
							"x mirror" : false,
							"x offset" : 0.0,
							"x scale" : 1.019531250,
							"x shear" : 0.0,
							"y mirror" : false,
							"y offset" : 0.0,
							"y scale" : 1.019531250,
							"y shear" : 0.0
						},
						
						{
							"add color" : "0x00110007",
							"angle" : -0.1265615671873093,
							"clip" : false,
							"filepath" : "1901_complex.json",
							"multi color" : "0x5b3cffff",
							"name" : "",
							"position" : 
							{
								"x" : 0.0,
								"y" : 75.93750
							},
							"tag" : "",
							"x mirror" : false,
							"x offset" : 0.0,
							"x scale" : 1.152774810791016,
							"x shear" : 0.0,
							"y mirror" : false,
							"y offset" : 0.0,
							"y scale" : 1.152774810791016,
							"y shear" : 0.0
						}
					],
					"time" : 15
				},
				
				{
					"actor" : 
					[
						
						{
							"add color" : "0x00000000",
							"angle" : 0.0,
							"clip" : false,
							"filepath" : "1888_complex.json",
							"multi color" : "0xffffff44",
							"name" : "",
							"position" : 
							{
								"x" : 0.0,
								"y" : 0.0
							},
							"tag" : "",
							"x mirror" : false,
							"x offset" : 0.0,
							"x scale" : 0.91894531250,
							"x shear" : 0.0,
							"y mirror" : false,
							"y offset" : 0.0,
							"y scale" : 0.91894531250,
							"y shear" : 0.0
						},
						
						{
							"add color" : "0x00110007",
							"angle" : -0.2226119786500931,
							"clip" : false,
							"filepath" : "1901_complex.json",
							"multi color" : "0x5b3cffff",
							"name" : "",
							"position" : 
							{
								"x" : -0.06250,
								"y" : 55.06250
							},
							"tag" : "",
							"x mirror" : false,
							"x offset" : 0.0,
							"x scale" : 1.101396799087524,
							"x shear" : 0.0,
							"y mirror" : false,
							"y offset" : 0.0,
							"y scale" : 1.101396799087524,
							"y shear" : 0.0
						}
					],
					"time" : 16
				},
				
				{
					"actor" : 
					[
						
						{
							"add color" : "0x00000000",
							"angle" : 0.0,
							"clip" : false,
							"filepath" : "1888_complex.json",
							"multi color" : "0xffffff47",
							"name" : "",
							"position" : 
							{
								"x" : 0.0,
								"y" : 0.0
							},
							"tag" : "",
							"x mirror" : false,
							"x offset" : 0.0,
							"x scale" : 0.8183593750,
							"x shear" : 0.0,
							"y mirror" : false,
							"y offset" : 0.0,
							"y scale" : 0.8183593750,
							"y shear" : 0.0
						},
						
						{
							"add color" : "0x00110007",
							"angle" : -0.3238160610198975,
							"clip" : false,
							"filepath" : "1901_complex.json",
							"multi color" : "0x5b3cffff",
							"name" : "",
							"position" : 
							{
								"x" : -0.06250,
								"y" : 32.6250
							},
							"tag" : "",
							"x mirror" : false,
							"x offset" : 0.0,
							"x scale" : 1.046580195426941,
							"x shear" : 0.0,
							"y mirror" : false,
							"y offset" : 0.0,
							"y scale" : 1.046580195426941,
							"y shear" : 0.0
						}
					],
					"time" : 17
				},
				
				{
					"actor" : 
					[
						
						{
							"add color" : "0x00000000",
							"angle" : 0.0,
							"clip" : false,
							"filepath" : "1888_complex.json",
							"multi color" : "0xffffff4c",
							"name" : "",
							"position" : 
							{
								"x" : 0.0,
								"y" : 0.0
							},
							"tag" : "",
							"x mirror" : false,
							"x offset" : 0.0,
							"x scale" : 0.71777343750,
							"x shear" : 0.0,
							"y mirror" : false,
							"y offset" : 0.0,
							"y scale" : 0.71777343750,
							"y shear" : 0.0
						},
						
						{
							"add color" : "0x00110007",
							"angle" : -0.4362692832946777,
							"clip" : false,
							"filepath" : "1901_complex.json",
							"multi color" : "0x5b3cffff",
							"name" : "",
							"position" : 
							{
								"x" : 0.0,
								"y" : 8.750
							},
							"tag" : "",
							"x mirror" : false,
							"x offset" : 0.0,
							"x scale" : 0.9891319870948792,
							"x shear" : 0.0,
							"y mirror" : false,
							"y offset" : 0.0,
							"y scale" : 0.9891319870948792,
							"y shear" : 0.0
						}
					],
					"time" : 18
				}
			],
			"name" : ""
		}
	],
	"name" : "xmas_bottleDrop"
}
