{
  "name": "", 
  "sprite": [
    {
      "angle": 0, 
      "filepath": "015021191618.png", 
      "name": "", 
      "position": {
        "x": 119.375, 
        "y": -52.5
      }, 
      "x mirror": false, 
      "x scale": 1.25, 
      "x shear": 0, 
      "y mirror": false, 
      "y scale": 1.25, 
      "y shear": 0
    }, 
    {
      "angle": 1.5707963267948966, 
      "filepath": "1178180912351872.png", 
      "name": "", 
      "position": {
        "x": 130.625, 
        "y": -30.625
      }, 
      "x mirror": false, 
      "x scale": 1.25, 
      "x shear": 0, 
      "y mirror": false, 
      "y scale": 1.25, 
      "y shear": 0
    }
  ]
}