{
	"layout" :
	{
		"col" : 3
	},
	"widget" :
	[
		{
			"type" : "text",
			"title" : "名字",
			"key" : "name"
		},
		{
			"type" : "choice",
			"title" : "阵营",
			"key" : "camp",
			"choices" :
			[
				{
					"value" : "enemy",
					"title" : "敌对"
				},
				{
					"value" : "neutral",
					"title" : "中立"
				},
				{
					"value" : "ally",
					"title" : "盟友"
				}				
			]
		},
		{
			"type" : "choice",
			"title" : "类型",
			"key" : "type",
			"choices" :
			[
				{
					"value" : "SaleEllickMember",
					"title" : "艾利克小兵"
				},
				{
					"value" : "SaleHenry",
					"title" : "亨利"
				},
				{
					"value" : "SaleHenryMember",
					"title" : "亨利小兵"
				},
				{
					"value" : "SaleDelia",
					"title" : "德利娅1"
				},
				{
					"value" : "SaleDelia2",
					"title" : "德利娅4"
				},
				{
					"value" : "SaleDeliaMember",
					"title" : "德利娅小兵"
				},
				{
					"value" : "SaleDeliaMember2",
					"title" : "德利娅小兵2"
				},
				{
					"value" : "SaleMader",
					"title" : "马德尔"
				},
				{
					"value" : "SaleMaderMember",
					"title" : "马德尔小兵"
				},
				{
					"value" : "SaleBerserkerSoldier",
					"title" : "狂战小兵"
				},

				{
					"value" : "SaleVillagerMale1",
					"title" : "村民-男"
				},
				{
					"value" : "SaleVillagerMale2",
					"title" : "村民-光头男"
				}			
			]
		},
		{
			"type" : "choice",
			"title" : "队伍",
			"key" : "squad",
			"choices" :
			[
				{
					"value" : "squad1",
					"title" : "队伍1"
				}
			]
		},
		{
			"type" : "check box",
			"title" : "队长",
			"key" : "leader",
			"default" : false
		},
		{
			"type" : "choice",
			"title" : "朝向",
			"key" : "dir",
			"choices" :
			[
				{
					"value" : "n",
					"title" : "北"
				},	
				{
					"value" : "ne",
					"title" : "东北"
				},	
				{
					"value" : "e",
					"title" : "东"
				},	
				{
					"value" : "se",
					"title" : "东南"
				},	
				{
					"value" : "s",
					"title" : "南"
				},	
				{
					"value" : "sw",
					"title" : "西南"
				},	
				{
					"value" : "w",
					"title" : "西"
				},
				{
					"value" : "nw",
					"title" : "西北"
				}
			]
		},
		{
			"type" : "check box",
			"title" : "场景AI",
			"key" : "scene_ai",
			"default" : false
		},
		{
			"type" : "check box",
			"title" : "上帝视角",
			"key" : "god_sight",
			"default" : false
		}
	]
}