
{
	"fps" : 30,
	"layer" : 
	[
		
		{
			"frame" : 
			[
				
				{
					"actor" : 
					[
						
						{
							"add color" : "0x00000000",
							"angle" : 0.0,
							"clip" : false,
							"filepath" : "lv5\\3_001.png",
							"multi color" : "0xffffffff",
							"name" : "_sprite34",
							"position" : 
							{
								"x" : 0.0,
								"y" : 0.0
							},
							"tag" : "",
							"x mirror" : false,
							"x offset" : -11.0,
							"x scale" : 1.0,
							"x shear" : 0.0,
							"y mirror" : false,
							"y offset" : 37.50,
							"y scale" : 1.0,
							"y shear" : 0.0
						}
					],
					"id" : 0,
					"skeleton" : null,
					"time" : 1,
					"tween" : false
				},
				
				{
					"actor" : 
					[
						
						{
							"add color" : "0x00000000",
							"angle" : 0.0,
							"clip" : false,
							"filepath" : "lv5\\3_006.png",
							"multi color" : "0xffffffff",
							"name" : "_sprite35",
							"position" : 
							{
								"x" : 0.0,
								"y" : 0.0
							},
							"tag" : "",
							"x mirror" : false,
							"x offset" : -12.50,
							"x scale" : 1.0,
							"x shear" : 0.0,
							"y mirror" : false,
							"y offset" : 38.0,
							"y scale" : 1.0,
							"y shear" : 0.0
						}
					],
					"id" : 0,
					"skeleton" : null,
					"time" : 4,
					"tween" : false
				},
				
				{
					"actor" : 
					[
						
						{
							"add color" : "0x00000000",
							"angle" : 0.0,
							"clip" : false,
							"filepath" : "lv5\\3_012.png",
							"multi color" : "0xffffffff",
							"name" : "_sprite36",
							"position" : 
							{
								"x" : 0.0,
								"y" : 0.0
							},
							"tag" : "",
							"x mirror" : false,
							"x offset" : -12.0,
							"x scale" : 1.0,
							"x shear" : 0.0,
							"y mirror" : false,
							"y offset" : 36.50,
							"y scale" : 1.0,
							"y shear" : 0.0
						}
					],
					"id" : 0,
					"skeleton" : null,
					"time" : 7,
					"tween" : false
				},
				
				{
					"actor" : 
					[
						
						{
							"add color" : "0x00000000",
							"angle" : 0.0,
							"clip" : false,
							"filepath" : "lv5\\3_012.png",
							"multi color" : "0xffffffff",
							"name" : "_sprite36",
							"position" : 
							{
								"x" : 0.0,
								"y" : 0.0
							},
							"tag" : "",
							"x mirror" : false,
							"x offset" : -12.0,
							"x scale" : 1.0,
							"x shear" : 0.0,
							"y mirror" : false,
							"y offset" : 36.50,
							"y scale" : 1.0,
							"y shear" : 0.0
						}
					],
					"id" : 0,
					"skeleton" : null,
					"time" : 9,
					"tween" : false
				}
			],
			"name" : "Layer12"
		}
	],
	"name" : "daoshi5_run_3"
}
