
{
	"name" : "",
	"sprite" : 
	[
		
		{
			"add color" : "0x00000000",
			"angle" : 0.0,
			"b trans" : "0x0000ffff",
			"clip" : false,
			"filepath" : "..\\png\\army_langqi_main.png",
			"g trans" : "0x00ff00ff",
			"multi color" : "0xffffffff",
			"name" : "_sprite0",
			"position" : 
			{
				"x" : 0.0,
				"y" : 0.0
			},
			"r trans" : "0xff0000ff",
			"tag" : "",
			"x mirror" : false,
			"x offset" : 0.0,
			"x scale" : 1.0,
			"x shear" : 0.0,
			"y mirror" : false,
			"y offset" : 0.0,
			"y scale" : 1.0,
			"y shear" : 0.0
		},
		
		{
			"add color" : "0x00000000",
			"angle" : 0.0,
			"b trans" : "0x0000ffff",
			"clip" : false,
			"filepath" : "..\\png\\army_langqi_part01.png",
			"g trans" : "0x00ff00ff",
			"multi color" : "0xffffffff",
			"name" : "_sprite1",
			"position" : 
			{
				"x" : -138.0,
				"y" : -9.0
			},
			"r trans" : "0xff0000ff",
			"tag" : "",
			"x mirror" : false,
			"x offset" : 0.0,
			"x scale" : 1.0,
			"x shear" : 0.0,
			"y mirror" : false,
			"y offset" : 0.0,
			"y scale" : 1.0,
			"y shear" : 0.0
		},
		
		{
			"add color" : "0x00000000",
			"angle" : 0.0,
			"b trans" : "0x0000ffff",
			"clip" : false,
			"filepath" : "..\\png\\army_langqi_part02.png",
			"g trans" : "0x00ff00ff",
			"multi color" : "0xffffffff",
			"name" : "_sprite2",
			"position" : 
			{
				"x" : -151.0,
				"y" : -174.0
			},
			"r trans" : "0xff0000ff",
			"tag" : "",
			"x mirror" : false,
			"x offset" : 0.0,
			"x scale" : 1.0,
			"x shear" : 0.0,
			"y mirror" : false,
			"y offset" : 0.0,
			"y scale" : 1.0,
			"y shear" : 0.0
		},
		
		{
			"add color" : "0x00000000",
			"angle" : 0.0,
			"b trans" : "0x0000ffff",
			"clip" : false,
			"filepath" : "..\\png\\army_langqi_part03.png",
			"g trans" : "0x00ff00ff",
			"multi color" : "0xffffffff",
			"name" : "_sprite3",
			"position" : 
			{
				"x" : -177.0,
				"y" : -254.50
			},
			"r trans" : "0xff0000ff",
			"tag" : "",
			"x mirror" : false,
			"x offset" : 0.0,
			"x scale" : 1.0,
			"x shear" : 0.0,
			"y mirror" : false,
			"y offset" : 0.0,
			"y scale" : 1.0,
			"y shear" : 0.0
		},
		
		{
			"add color" : "0x00000000",
			"angle" : 0.0,
			"b trans" : "0x0000ffff",
			"clip" : false,
			"filepath" : "..\\png\\army_langqi_part04.png",
			"g trans" : "0x00ff00ff",
			"multi color" : "0xffffffff",
			"name" : "_sprite4",
			"position" : 
			{
				"x" : 23.0,
				"y" : -200.0
			},
			"r trans" : "0xff0000ff",
			"tag" : "",
			"x mirror" : false,
			"x offset" : 0.0,
			"x scale" : 1.0,
			"x shear" : 0.0,
			"y mirror" : false,
			"y offset" : 0.0,
			"y scale" : 1.0,
			"y shear" : 0.0
		},
		
		{
			"add color" : "0x00000000",
			"angle" : 0.0,
			"b trans" : "0x0000ffff",
			"clip" : false,
			"filepath" : "..\\png\\army_langqi_part05.png",
			"g trans" : "0x00ff00ff",
			"multi color" : "0xffffffff",
			"name" : "_sprite5",
			"position" : 
			{
				"x" : 196.50,
				"y" : -167.0
			},
			"r trans" : "0xff0000ff",
			"tag" : "",
			"x mirror" : false,
			"x offset" : 0.0,
			"x scale" : 1.0,
			"x shear" : 0.0,
			"y mirror" : false,
			"y offset" : 0.0,
			"y scale" : 1.0,
			"y shear" : 0.0
		},
		
		{
			"add color" : "0x00000000",
			"angle" : 0.0,
			"b trans" : "0x0000ffff",
			"clip" : false,
			"filepath" : "..\\png\\army_langqi_part06.png",
			"g trans" : "0x00ff00ff",
			"multi color" : "0xffffffff",
			"name" : "_sprite6",
			"position" : 
			{
				"x" : 290.50,
				"y" : -248.50
			},
			"r trans" : "0xff0000ff",
			"tag" : "",
			"x mirror" : false,
			"x offset" : 0.0,
			"x scale" : 1.0,
			"x shear" : 0.0,
			"y mirror" : false,
			"y offset" : 0.0,
			"y scale" : 1.0,
			"y shear" : 0.0
		},
		
		{
			"add color" : "0x00000000",
			"angle" : 0.0,
			"b trans" : "0x0000ffff",
			"clip" : false,
			"filepath" : "..\\png\\army_langqi_part07.png",
			"g trans" : "0x00ff00ff",
			"multi color" : "0xffffffff",
			"name" : "_sprite7",
			"position" : 
			{
				"x" : -75.50,
				"y" : -354.50
			},
			"r trans" : "0xff0000ff",
			"tag" : "",
			"x mirror" : false,
			"x offset" : 0.0,
			"x scale" : 1.0,
			"x shear" : 0.0,
			"y mirror" : false,
			"y offset" : 0.0,
			"y scale" : 1.0,
			"y shear" : 0.0
		},
		
		{
			"add color" : "0x00000000",
			"angle" : 0.0,
			"b trans" : "0x0000ffff",
			"clip" : false,
			"filepath" : "..\\png\\army_langqi_part08.png",
			"g trans" : "0x00ff00ff",
			"multi color" : "0xffffffff",
			"name" : "_sprite8",
			"position" : 
			{
				"x" : 77.50,
				"y" : -406.0
			},
			"r trans" : "0xff0000ff",
			"tag" : "",
			"x mirror" : false,
			"x offset" : 0.0,
			"x scale" : 1.0,
			"x shear" : 0.0,
			"y mirror" : false,
			"y offset" : 0.0,
			"y scale" : 1.0,
			"y shear" : 0.0
		},
		
		{
			"add color" : "0x00000000",
			"angle" : 0.0,
			"b trans" : "0x0000ffff",
			"clip" : false,
			"filepath" : "..\\png\\army_langqi_part09.png",
			"g trans" : "0x00ff00ff",
			"multi color" : "0xffffffff",
			"name" : "_sprite9",
			"position" : 
			{
				"x" : 240.50,
				"y" : -351.50
			},
			"r trans" : "0xff0000ff",
			"tag" : "",
			"x mirror" : false,
			"x offset" : 0.0,
			"x scale" : 1.0,
			"x shear" : 0.0,
			"y mirror" : false,
			"y offset" : 0.0,
			"y scale" : 1.0,
			"y shear" : 0.0
		}
	],
	"use_render_cache" : false,
	"xmax" : 0.0,
	"xmin" : 0.0,
	"ymax" : 0.0,
	"ymin" : 0.0
}
