
{
	"name" : "char_info_xueying",
	"sprite" : 
	[
		
		{
			"add color" : "0x00000000",
			"angle" : 0.0,
			"b trans" : "0x0000ffff",
			"clip" : false,
			"filepath" : "..\\png\\6196-tongyong-1.png",
			"g trans" : "0x00ff00ff",
			"multi color" : "0xffffffff",
			"name" : "",
			"position" : 
			{
				"x" : 19.54999923706055,
				"y" : 60.55001068115234
			},
			"r trans" : "0xff0000ff",
			"tag" : "",
			"x mirror" : false,
			"x offset" : 0.0,
			"x scale" : 0.6999999880790710,
			"x shear" : 0.0,
			"y mirror" : false,
			"y offset" : 0.0,
			"y scale" : 0.6999999880790710,
			"y shear" : 0.0
		},
		
		{
			"add color" : "0x00000000",
			"angle" : 0.0,
			"b trans" : "0x0000ffff",
			"clip" : false,
			"filepath" : "..\\png\\6196-tongyong-2.png",
			"g trans" : "0x00ff00ff",
			"multi color" : "0xffffffff",
			"name" : "",
			"position" : 
			{
				"x" : -93.95001220703125,
				"y" : -35.34999084472656
			},
			"r trans" : "0xff0000ff",
			"tag" : "",
			"x mirror" : false,
			"x offset" : 0.0,
			"x scale" : 0.6999999880790710,
			"x shear" : 0.0,
			"y mirror" : false,
			"y offset" : 0.0,
			"y scale" : 0.6999999880790710,
			"y shear" : 0.0
		},
		
		{
			"add color" : "0x00000000",
			"angle" : 0.0,
			"b trans" : "0x0000ffff",
			"clip" : false,
			"filepath" : "..\\png\\6196-tongyong-3.png",
			"g trans" : "0x00ff00ff",
			"multi color" : "0xffffffff",
			"name" : "",
			"position" : 
			{
				"x" : 136.7999877929688,
				"y" : -21.69998931884766
			},
			"r trans" : "0xff0000ff",
			"tag" : "",
			"x mirror" : false,
			"x offset" : 0.0,
			"x scale" : 0.6999999880790710,
			"x shear" : 0.0,
			"y mirror" : false,
			"y offset" : 0.0,
			"y scale" : 0.6999999880790710,
			"y shear" : 0.0
		},
		
		{
			"add color" : "0x00000000",
			"angle" : 0.0,
			"b trans" : "0x0000ffff",
			"clip" : false,
			"filepath" : "..\\png\\6196-tongyong-4.png",
			"g trans" : "0x00ff00ff",
			"multi color" : "0xffffffff",
			"name" : "",
			"position" : 
			{
				"x" : 22.04999923706055,
				"y" : 181.3000030517578
			},
			"r trans" : "0xff0000ff",
			"tag" : "",
			"x mirror" : false,
			"x offset" : 0.0,
			"x scale" : 0.6999999880790710,
			"x shear" : 0.0,
			"y mirror" : false,
			"y offset" : 0.0,
			"y scale" : 0.6999999880790710,
			"y shear" : 0.0
		},
		
		{
			"add color" : "0x00000000",
			"angle" : 0.0,
			"b trans" : "0x0000ffff",
			"clip" : false,
			"filepath" : "..\\png\\6196-tongyong-5.png",
			"g trans" : "0x00ff00ff",
			"multi color" : "0xffffffff",
			"name" : "",
			"position" : 
			{
				"x" : -86.15000152587891,
				"y" : 92.40000915527344
			},
			"r trans" : "0xff0000ff",
			"tag" : "",
			"x mirror" : false,
			"x offset" : 0.0,
			"x scale" : 0.6999999880790710,
			"x shear" : 0.0,
			"y mirror" : false,
			"y offset" : 0.0,
			"y scale" : 0.6999999880790710,
			"y shear" : 0.0
		},
		
		{
			"add color" : "0x00000000",
			"angle" : 0.0,
			"b trans" : "0x0000ffff",
			"clip" : false,
			"filepath" : "..\\png\\6196-tongyong-6.png",
			"g trans" : "0x00ff00ff",
			"multi color" : "0xffffffff",
			"name" : "",
			"position" : 
			{
				"x" : 128.750,
				"y" : 92.40000915527344
			},
			"r trans" : "0xff0000ff",
			"tag" : "",
			"x mirror" : false,
			"x offset" : 0.0,
			"x scale" : 0.6999999880790710,
			"x shear" : 0.0,
			"y mirror" : false,
			"y offset" : 0.0,
			"y scale" : 0.6999999880790710,
			"y shear" : 0.0
		}
	],
	"use_render_cache" : false,
	"xmax" : 0.0,
	"xmin" : 0.0,
	"ymax" : 0.0,
	"ymin" : 0.0
}
