
{
	"name" : "",
	"sprite" : 
	[
		
		{
			"add color" : "0x00000000",
			"angle" : 0.0,
			"clip" : true,
			"filepath" : "girl_rank_slide_complex.json",
			"multi color" : "0xffffffff",
			"name" : "item_slide",
			"position" : 
			{
				"x" : -2.516510009765625,
				"y" : 208.3028259277344
			},
			"tag" : "",
			"x mirror" : false,
			"x offset" : 0.0,
			"x scale" : 1.0,
			"x shear" : 0.0,
			"y mirror" : false,
			"y offset" : -1956.50,
			"y scale" : 1.0,
			"y shear" : 0.0
		},
		
		{
			"add color" : "0x00000000",
			"angle" : 0.0,
			"clip" : false,
			"filepath" : "girl_rank_item_complex.json",
			"multi color" : "0xffffffff",
			"name" : "item_self",
			"position" : 
			{
				"x" : -2.516510009765625,
				"y" : -258.9698181152344
			},
			"tag" : "",
			"x mirror" : false,
			"x offset" : 0.0,
			"x scale" : 1.0,
			"x shear" : 0.0,
			"y mirror" : false,
			"y offset" : -6.500030517578125,
			"y scale" : 1.0,
			"y shear" : 0.0
		},
		
		{
			"add color" : "0x00000000",
			"angle" : 0.0,
			"clip" : false,
			"filepath" : "rank_line_complex.json",
			"multi color" : "0xffffffff",
			"name" : "_sprite421",
			"position" : 
			{
				"x" : -2.516510009765625,
				"y" : -210.7879943847656
			},
			"tag" : "",
			"x mirror" : false,
			"x offset" : 0.0,
			"x scale" : 1.0,
			"x shear" : 0.0,
			"y mirror" : false,
			"y offset" : 0.0,
			"y scale" : 1.0,
			"y shear" : 0.0
		}
	],
	"xmax" : 405.0,
	"xmin" : -410.0,
	"ymax" : 255.0,
	"ymin" : -195.0
}
