
{
	"name" : "building_1013_lv6",
	"sprite" : 
	[
		{
			"add color" : "",
			"angle" : 0.0,
			"filepath" : "..\\..\\pngs\\1107_1.PNG",
			"multi color" : "",
			"name" : "",
			"position" : 
			{
				"x" : -13.0,
				"y" : -15.0
			},
			"x mirror" : false,
			"x scale" : 0.6499999761581421,
			"x shear" : 0.0,
			"y mirror" : false,
			"y scale" : 0.6499999761581421,
			"y shear" : 0.0
		},
		
		{
			"angle" : 0.0,
			"filepath" : "..\\..\\pngs\\1013_3_lv1_22.png",
			"name" : "",
			"position" : 
			{
				"x" : 0.0,
				"y" : 0.0
			},
			"x mirror" : false,
			"x scale" : 1.0,
			"x shear" : 0.0,
			"y mirror" : false,
			"y scale" : 1.0,
			"y shear" : 0.0
		},
		
		{
			"angle" : 0.0,
			"filepath" : "..\\..\\pngs\\1013_3_lv6_1.png",
			"name" : "",
			"position" : 
			{
				"x" : 0.0,
				"y" : 0.0
			},
			"x mirror" : false,
			"x scale" : 1.0,
			"x shear" : 0.0,
			"y mirror" : false,
			"y scale" : 1.0,
			"y shear" : 0.0
		},
		
		{
			"angle" : 0.0,
			"filepath" : "..\\..\\pngs\\1013_3_lv1_21.png",
			"name" : "",
			"position" : 
			{
				"x" : 0.0,
				"y" : 0.0
			},
			"x mirror" : false,
			"x scale" : 1.0,
			"x shear" : 0.0,
			"y mirror" : false,
			"y scale" : 1.0,
			"y shear" : 0.0
		},
		
		{
			"angle" : 0.0,
			"filepath" : "building_1013_ani_1_anim.json",
			"name" : "resource",
			"position" : 
			{
				"x" : 0.0,
				"y" : 0.0
			},
			"x mirror" : false,
			"x scale" : 1.0,
			"x shear" : 0.0,
			"y mirror" : false,
			"y scale" : 1.0,
			"y shear" : 0.0
		}
	]
}
